pyxrk-0.0.2.dist-info/METADATA
pyxrk-0.0.2.dist-info/WHEEL
pyxrk-0.0.2.dist-info/license_files/LICENSE
pyxrk/run.py
pyxrk/__init__.py
pyxrk/py.typed
pyxrk/pyxrk_raw.pyi
pyxrk/pyxrk_raw.cpython-310-darwin.so
pyxrk-0.0.2.dist-info/RECORD
