Metadata-Version: 2.1
Name: pyxrk
Version: 0.0.2
Classifier: Programming Language :: Rust
Classifier: Programming Language :: Python :: Implementation :: CPython
Classifier: Programming Language :: Python :: Implementation :: PyPy
Requires-Dist: pyarrow
Requires-Dist: black ; extra == 'test'
Requires-Dist: isort ; extra == 'test'
Requires-Dist: mypy ; extra == 'test'
Requires-Dist: ruff ; extra == 'test'
Requires-Dist: pytest ; extra == 'test'
Provides-Extra: test
License-File: LICENSE
Author: Joe Portela <jportela14@gmail.com>
Author-email: Joe Portela <jportela14@gmail.com>
Requires-Python: >=3.7
